{
    "filename": "D:/DELL/Downloads/51\\GX0102950358.jpg",
    "height": 1520,
    "width": 2704,
    "scaleratio": 0.48261834319526625,
    "annots": [
        {
            "personID": 0,
            "bbox": [
                1483.5739463601533,
                501.4314176245211,
                2007.7977011494254,
                772.8674329501916
            ],
            "keypoints": [
                [
                    1922.8444444444444,
                    578.096551724138,
                    1.0
                ],
                [
                    1895.9080459770116,
                    596.744827586207,
                    1.0
                ],
                [
                    0.0,
                    0.0,
                    0.0
                ],
                [
                    0.0,
                    0.0,
                    0.0
                ],
                [
                    0.0,
                    0.0,
                    0.0
                ],
                [
                    1868.9716475095786,
                    644.4015325670498,
                    1.0
                ],
                [
                    1933.2045977011494,
                    638.1854406130268,
                    1.0
                ],
                [
                    1962.2130268199235,
                    648.5455938697319,
                    1.0
                ],
                [
                    1769.5141762452108,
                    621.6091954022988,
                    1.0
                ],
                [
                    1744.6498084291188,
                    656.8337164750958,
                    1.0
                ],
                [
                    1692.849042145594,
                    692.0582375478928,
                    1.0
                ],
                [
                    1746.7218390804599,
                    675.4819923371648,
                    1.0
                ],
                [
                    1651.408429118774,
                    689.9862068965517,
                    1.0
                ],
                [
                    1564.3831417624522,
                    658.9057471264368,
                    1.0
                ],
                [
                    1539.5187739463602,
                    654.7616858237548,
                    1.0
                ],
                [
                    1692.849042145594,
                    735.5708812260536,
                    1.0
                ],
                [
                    1985.0053639846744,
                    646.4735632183908,
                    1.0
                ],
                [
                    0.0,
                    0.0,
                    0.0
                ]
            ]
        }
    ],
    "detect_feet": false,
    "isKeyframe": false
}