{
    "filename": "E:/Filez/76\\GX0100870891.jpg",
    "height": 1520,
    "width": 2704,
    "scaleratio": 0.48261834319526625,
    "annots": [
        {
            "personID": 0,
            "bbox": [
                563.6403269754768,
                77.36239782016348,
                2033.525885558583,
                788.3596730245231
            ],
            "keypoints": [
                [
                    1865.9072265625,
                    281.8201599121094,
                    1.0
                ],
                [
                    1718.55029296875,
                    292.8719177246094,
                    1.0
                ],
                [
                    1731.444091796875,
                    366.5503845214844,
                    1.0
                ],
                [
                    1757.2315673828127,
                    513.9073486328125,
                    1.0
                ],
                [
                    1847.4876708984375,
                    602.3214721679688,
                    1.0
                ],
                [
                    1644.871826171875,
                    300.2397766113281,
                    1.0
                ],
                [
                    1687.2369384765625,
                    396.02178955078125,
                    1.0
                ],
                [
                    1740.6539306640625,
                    506.5394897460937,
                    1.0
                ],
                [
                    1307.7928466796875,
                    412.59942626953125,
                    1.0
                ],
                [
                    1088.599365234375,
                    539.69482421875,
                    1.0
                ],
                [
                    828.8828125,
                    598.6375732421875,
                    1.0
                ],
                [
                    1265.427734375,
                    388.6539306640625,
                    1.0
                ],
                [
                    1105.1771240234375,
                    477.068115234375,
                    1.0
                ],
                [
                    834.40869140625,
                    528.6430053710938,
                    1.0
                ],
                [
                    797.5694580078125,
                    582.0599365234375,
                    1.0
                ],
                [
                    716.5231323242188,
                    652.054443359375,
                    1.0
                ],
                [
                    1748.021728515625,
                    554.4304809570312,
                    1.0
                ],
                [
                    1926.6920166015625,
                    699.9454956054688,
                    1.0
                ]
            ]
        }
    ],
    "detect_feet": false,
    "isKeyframe": false
}