{
    "filename": "D:/63\\GX0101000465.jpg",
    "height": 1520,
    "width": 2704,
    "scaleratio": 0.643491124260355,
    "annots": [
        {
            "personID": 0,
            "bbox": [
                377.6275862068965,
                192.69885057471265,
                1383.0804597701149,
                946.4
            ],
            "keypoints": [
                [
                    1137.5448275862068,
                    320.1287356321839,
                    1.0
                ],
                [
                    1101.8022988505747,
                    418.03218390804597,
                    1.0
                ],
                [
                    1134.4367816091954,
                    480.19310344827585,
                    1.0
                ],
                [
                    1154.6390804597702,
                    561.0022988505747,
                    1.0
                ],
                [
                    1193.4896551724137,
                    621.6091954022988,
                    1.0
                ],
                [
                    1036.5333333333333,
                    449.1126436781609,
                    1.0
                ],
                [
                    913.7655172413793,
                    522.1517241379311,
                    1.0
                ],
                [
                    808.0919540229885,
                    570.3264367816092,
                    1.0
                ],
                [
                    874.9149425287357,
                    587.4206896551724,
                    1.0
                ],
                [
                    685.3241379310344,
                    651.135632183908,
                    1.0
                ],
                [
                    576.5425287356321,
                    839.1724137931035,
                    1.0
                ],
                [
                    842.2804597701149,
                    564.1103448275862,
                    1.0
                ],
                [
                    612.2850574712644,
                    599.8528735632184,
                    1.0
                ],
                [
                    547.016091954023,
                    790.9977011494253,
                    1.0
                ],
                [
                    492.62528735632185,
                    871.8068965517241,
                    1.0
                ],
                [
                    455.3287356321839,
                    873.3609195402298,
                    1.0
                ],
                [
                    745.9310344827586,
                    629.3793103448276,
                    1.0
                ],
                [
                    1204.367816091954,
                    679.1080459770114,
                    1.0
                ]
            ]
        }
    ],
    "detect_feet": false,
    "isKeyframe": false
}