{
    "filename": "D:/63\\GX0101001041.jpg",
    "height": 1520,
    "width": 2704,
    "scaleratio": 0.643491124260355,
    "annots": [
        {
            "personID": 0,
            "bbox": [
                290.6022988505747,
                80.80919540229885,
                1353.5540229885057,
                832.9563218390805
            ],
            "keypoints": [
                [
                    1149.9770114942528,
                    250.19770114942528,
                    1.0
                ],
                [
                    1131.328735632184,
                    315.46666666666664,
                    1.0
                ],
                [
                    1123.558620689655,
                    388.5057471264368,
                    1.0
                ],
                [
                    1076.9379310344827,
                    463.0988505747126,
                    1.0
                ],
                [
                    1042.7494252873564,
                    498.8413793103448,
                    1.0
                ],
                [
                    1108.0183908045976,
                    324.79080459770114,
                    1.0
                ],
                [
                    997.6827586206896,
                    363.6413793103448,
                    1.0
                ],
                [
                    893.5632183908045,
                    394.72183908045974,
                    1.0
                ],
                [
                    905.9954022988505,
                    456.88275862068963,
                    1.0
                ],
                [
                    728.8367816091954,
                    486.40919540229885,
                    1.0
                ],
                [
                    609.1770114942528,
                    634.0413793103448,
                    1.0
                ],
                [
                    919.9816091954023,
                    480.19310344827585,
                    1.0
                ],
                [
                    744.3770114942529,
                    508.1655172413793,
                    1.0
                ],
                [
                    724.1747126436782,
                    705.5264367816092,
                    1.0
                ],
                [
                    630.9333333333333,
                    761.471264367816,
                    1.0
                ],
                [
                    503.50344827586207,
                    669.783908045977,
                    1.0
                ],
                [
                    851.6045977011494,
                    441.3425287356322,
                    1.0
                ],
                [
                    1027.2091954022987,
                    511.2735632183908,
                    1.0
                ]
            ]
        }
    ],
    "detect_feet": false,
    "isKeyframe": false
}