{
    "filename": "D:/DELL/Downloads/52\\GX0102950741.jpg",
    "height": 1520,
    "width": 2704,
    "scaleratio": 0.48261834319526625,
    "annots": [
        {
            "personID": 0,
            "bbox": [
                1431.7731800766285,
                383.3256704980843,
                2020.2298850574714,
                830.8842911877394
            ],
            "keypoints": [
                [
                    0.0,
                    0.0,
                    0.0
                ],
                [
                    1817.1708812260538,
                    598.8168582375479,
                    1.0
                ],
                [
                    1769.5141762452108,
                    582.2406130268199,
                    1.0
                ],
                [
                    0.0,
                    0.0,
                    0.0
                ],
                [
                    0.0,
                    0.0,
                    0.0
                ],
                [
                    1873.1157088122607,
                    631.9693486590039,
                    1.0
                ],
                [
                    1844.1072796934866,
                    687.9141762452108,
                    1.0
                ],
                [
                    1823.3869731800767,
                    698.2743295019158,
                    1.0
                ],
                [
                    1676.272796934866,
                    648.5455938697319,
                    1.0
                ],
                [
                    1585.103448275862,
                    687.9141762452108,
                    1.0
                ],
                [
                    1512.5823754789274,
                    768.7233716475096,
                    1.0
                ],
                [
                    1736.361685823755,
                    677.5540229885057,
                    1.0
                ],
                [
                    1667.984674329502,
                    652.6896551724138,
                    1.0
                ],
                [
                    1578.8873563218392,
                    712.7785440613027,
                    1.0
                ],
                [
                    1510.5103448275863,
                    704.4904214559388,
                    1.0
                ],
                [
                    1485.6459770114943,
                    789.4436781609196,
                    1.0
                ],
                [
                    1804.7386973180078,
                    698.2743295019158,
                    1.0
                ],
                [
                    0.0,
                    0.0,
                    0.0
                ]
            ]
        }
    ],
    "detect_feet": false,
    "isKeyframe": false
}