{
    "filename": "D:/annot_tools/annot_tools/bjwj/61\\GX0101080208.jpg",
    "height": 1520,
    "width": 2704,
    "scaleratio": 0.643491124260355,
    "annots": [
        {
            "personID": 0,
            "bbox": [
                522.1517241379311,
                585.8666666666667,
                2129.0114942528735,
                1229.232183908046
            ],
            "keypoints": [
                [
                    1062.95166015625,
                    822.078125,
                    1.0
                ],
                [
                    1120.4505615234375,
                    804.9838867187501,
                    1.0
                ],
                [
                    1174.84130859375,
                    832.956298828125,
                    1.0
                ],
                [
                    1052.073486328125,
                    832.956298828125,
                    1.0
                ],
                [
                    848.4965209960938,
                    769.2413330078125,
                    1.0
                ],
                [
                    1167.0711669921875,
                    826.7401733398438,
                    1.0
                ],
                [
                    1050.51953125,
                    836.0643310546875,
                    1.0
                ],
                [
                    829.8482666015625,
                    763.0252685546875,
                    1.0
                ],
                [
                    1488.75390625,
                    966.6022338867189,
                    1.0
                ],
                [
                    1656.5885009765627,
                    1033.42529296875,
                    1.0
                ],
                [
                    1944.0826416015627,
                    1045.857421875,
                    1.0
                ],
                [
                    1431.255126953125,
                    963.4942016601562,
                    1.0
                ],
                [
                    1701.6551513671877,
                    1067.61376953125,
                    1.0
                ],
                [
                    1978.2712402343748,
                    1073.829833984375,
                    1.0
                ],
                [
                    2062.1884765625,
                    1171.7332763671875,
                    1.0
                ],
                [
                    2054.418212890625,
                    1142.2069091796875,
                    1.0
                ],
                [
                    781.6735229492188,
                    725.7286987304688,
                    1.0
                ],
                [
                    775.4574584960938,
                    705.5264282226562,
                    1.0
                ]
            ]
        }
    ],
    "detect_feet": false,
    "isKeyframe": false
}