{
    "filename": "D:/annot_tools/annot_tools/bjwj/61\\GX0101080680.jpg",
    "height": 1520,
    "width": 2704,
    "scaleratio": 0.643491124260355,
    "annots": [
        {
            "personID": 0,
            "bbox": [
                949.5080459770115,
                710.1885057471264,
                1839.9632183908045,
                1328.6896551724137
            ],
            "keypoints": [
                [
                    1067.61376953125,
                    892.0091552734376,
                    1.0
                ],
                [
                    1193.4896240234375,
                    862.4827270507814,
                    1.0
                ],
                [
                    1221.4620361328125,
                    879.5769653320312,
                    1.0
                ],
                [
                    1126.6666259765625,
                    1044.303466796875,
                    1.0
                ],
                [
                    1025.6551513671875,
                    952.6160278320312,
                    1.0
                ],
                [
                    1204.3677978515625,
                    902.8873291015626,
                    1.0
                ],
                [
                    1115.7884521484375,
                    1052.073486328125,
                    1.0
                ],
                [
                    1031.8712158203125,
                    965.0482177734375,
                    1.0
                ],
                [
                    1471.65966796875,
                    958.8321533203125,
                    1.0
                ],
                [
                    1536.9287109375,
                    1097.14013671875,
                    1.0
                ],
                [
                    1600.6436767578123,
                    935.5217895507812,
                    1.0
                ],
                [
                    1493.416015625,
                    974.3723754882812,
                    1.0
                ],
                [
                    1650.372314453125,
                    1171.7332763671875,
                    1.0
                ],
                [
                    1628.6160888671875,
                    943.2919311523439,
                    1.0
                ],
                [
                    1693.8850097656248,
                    926.1976928710936,
                    1.0
                ],
                [
                    1675.2366943359375,
                    919.9815673828126,
                    1.0
                ],
                [
                    958.8321533203125,
                    946.3999633789062,
                    1.0
                ],
                [
                    954.1701049804689,
                    947.9539794921875,
                    1.0
                ]
            ]
        }
    ],
    "detect_feet": false,
    "isKeyframe": false
}