{
    "filename": "D:/annot_tools/annot_tools/bjwj/61\\GX0101080160.jpg",
    "height": 1520,
    "width": 2704,
    "scaleratio": 0.643491124260355,
    "annots": [
        {
            "personID": 0,
            "bbox": [
                879.5770114942528,
                512.8275862068965,
                2049.7563218390806,
                1317.8114942528734
            ],
            "keypoints": [
                [
                    0.0,
                    0.0,
                    0.0
                ],
                [
                    0.0,
                    0.0,
                    0.0
                ],
                [
                    1094.0321044921875,
                    705.5264282226562,
                    1.0
                ],
                [
                    1196.59765625,
                    845.3884887695314,
                    1.0
                ],
                [
                    1083.1539306640625,
                    865.5907592773438,
                    1.0
                ],
                [
                    1123.55859375,
                    710.1884765625,
                    1.0
                ],
                [
                    1182.6114501953125,
                    851.6045532226564,
                    1.0
                ],
                [
                    1033.42529296875,
                    878.02294921875,
                    1.0
                ],
                [
                    1333.3516845703125,
                    923.089599609375,
                    1.0
                ],
                [
                    1479.4298095703125,
                    1061.397705078125,
                    1.0
                ],
                [
                    1745.167724609375,
                    1114.2344970703125,
                    1.0
                ],
                [
                    1333.3516845703125,
                    910.6574096679686,
                    1.0
                ],
                [
                    1484.0919189453125,
                    1080.0458984375,
                    1.0
                ],
                [
                    1807.3286132812502,
                    1106.46435546875,
                    1.0
                ],
                [
                    1841.5172119140623,
                    1209.02978515625,
                    1.0
                ],
                [
                    1832.1929931640623,
                    1230.7861328125,
                    1.0
                ],
                [
                    1045.857421875,
                    979.0344238281249,
                    1.0
                ],
                [
                    1034.979248046875,
                    955.7241210937499,
                    1.0
                ]
            ]
        }
    ],
    "detect_feet": false,
    "isKeyframe": false
}