{
    "filename": "E:/Filez/76\\GX0100870363.jpg",
    "height": 1520,
    "width": 2704,
    "scaleratio": 0.48261834319526625,
    "annots": [
        {
            "personID": 0,
            "bbox": [
                652.0544959128065,
                69.99455040871933,
                2459.019073569482,
                486.2779291553133
            ],
            "keypoints": [
                [
                    1889.8527832031248,
                    361.0245056152344,
                    1.0
                ],
                [
                    1832.751953125,
                    292.8719177246094,
                    1.0
                ],
                [
                    1853.0135498046875,
                    193.40599060058594,
                    1.0
                ],
                [
                    2120.097900390625,
                    250.5068054199219,
                    1.0
                ],
                [
                    2195.618408203125,
                    228.40325927734375,
                    1.0
                ],
                [
                    1899.0626220703125,
                    191.56402587890625,
                    1.0
                ],
                [
                    2070.364990234375,
                    221.03541564941406,
                    1.0
                ],
                [
                    2230.6157226562495,
                    228.40325927734375,
                    1.0
                ],
                [
                    1471.7274169921875,
                    206.29971313476562,
                    1.0
                ],
                [
                    1119.9127197265625,
                    191.56402587890625,
                    1.0
                ],
                [
                    873.0899047851562,
                    138.1471405029297,
                    1.0
                ],
                [
                    1401.73291015625,
                    154.72479248046875,
                    1.0
                ],
                [
                    1143.8582763671875,
                    152.88282775878906,
                    1.0
                ],
                [
                    887.8255615234375,
                    95.78201293945312,
                    1.0
                ],
                [
                    777.307861328125,
                    110.51770782470703,
                    1.0
                ],
                [
                    738.6266479492188,
                    132.62124633789062,
                    1.0
                ],
                [
                    2296.92626953125,
                    180.5122528076172,
                    1.0
                ],
                [
                    2284.0327148437495,
                    217.3514862060547,
                    1.0
                ]
            ]
        }
    ],
    "detect_feet": false,
    "isKeyframe": false
}