{
    "filename": "E:/Filez/76\\GX0100870406.jpg",
    "height": 1520,
    "width": 2704,
    "scaleratio": 0.48261834319526625,
    "annots": [
        {
            "personID": 0,
            "bbox": [
                784.675749318801,
                77.36239782016348,
                1983.792915531335,
                489.96185286103537
            ],
            "keypoints": [
                [
                    1683.5531335149863,
                    384.97002724795635,
                    1.0
                ],
                [
                    1690.9209809264303,
                    313.133514986376,
                    1.0
                ],
                [
                    1700.1307901907355,
                    244.98092643051768,
                    1.0
                ],
                [
                    1926.692098092643,
                    307.60762942779286,
                    1.0
                ],
                [
                    1906.4305177111714,
                    232.08719346049045,
                    1.0
                ],
                [
                    1626.4523160762942,
                    154.72479564032696,
                    1.0
                ],
                [
                    1764.5994550408718,
                    163.93460490463212,
                    1.0
                ],
                [
                    1889.8528610354222,
                    202.61580381471387,
                    1.0
                ],
                [
                    1434.8882833787466,
                    186.03814713896455,
                    1.0
                ],
                [
                    1210.1689373297002,
                    256.0326975476839,
                    1.0
                ],
                [
                    1009.3950953678473,
                    283.6621253405994,
                    1.0
                ],
                [
                    1357.525885558583,
                    134.46321525885557,
                    1.0
                ],
                [
                    1162.2779291553131,
                    173.14441416893732,
                    1.0
                ],
                [
                    932.0326975476838,
                    215.50953678474113,
                    1.0
                ],
                [
                    827.0408719346049,
                    276.29427792915527,
                    1.0
                ],
                [
                    867.5640326975476,
                    375.7602179836512,
                    1.0
                ],
                [
                    1897.2207084468664,
                    228.40326975476836,
                    1.0
                ],
                [
                    1906.4305177111714,
                    252.34877384196182,
                    1.0
                ]
            ]
        }
    ],
    "detect_feet": false,
    "isKeyframe": false
}