{
    "filename": "E:/Filez/76\\GX0100870090.jpg",
    "height": 1520,
    "width": 2704,
    "scaleratio": 0.48261834319526625,
    "annots": [
        {
            "personID": 0,
            "bbox": [
                217.35149863760216,
                187.8801089918256,
                1735.1280653950953,
                718.3651226158038
            ],
            "keypoints": [
                [
                    716.5231607629427,
                    528.6430517711171,
                    1.0
                ],
                [
                    753.3623978201634,
                    440.2288828337874,
                    1.0
                ],
                [
                    792.043596730245,
                    362.86648501362396,
                    1.0
                ],
                [
                    591.2697547683923,
                    412.5994550408719,
                    1.0
                ],
                [
                    504.69754768392363,
                    407.0735694822888,
                    1.0
                ],
                [
                    705.4713896457765,
                    379.4441416893733,
                    1.0
                ],
                [
                    510.2234332425068,
                    421.80926430517707,
                    1.0
                ],
                [
                    451.28065395095365,
                    408.9155313351498,
                    1.0
                ],
                [
                    1151.226158038147,
                    384.97002724795635,
                    1.0
                ],
                [
                    1326.2125340599455,
                    464.1743869209809,
                    1.0
                ],
                [
                    1506.7247956403269,
                    523.117166212534,
                    1.0
                ],
                [
                    1097.809264305177,
                    329.7111716621253,
                    1.0
                ],
                [
                    1340.9482288828337,
                    480.7520435967302,
                    1.0
                ],
                [
                    1556.4577656675747,
                    552.5885558583105,
                    1.0
                ],
                [
                    1648.5558583106265,
                    617.0572207084468,
                    1.0
                ],
                [
                    1628.2942779291552,
                    582.0599455040872,
                    1.0
                ],
                [
                    377.6021798365122,
                    386.8119891008174,
                    1.0
                ],
                [
                    436.54495912806533,
                    429.1771117166212,
                    1.0
                ]
            ]
        }
    ],
    "detect_feet": false,
    "isKeyframe": false
}