{
    "filename": "D:/DELL/Downloads/73\\GX0101111686.jpg",
    "height": 1520,
    "width": 2704,
    "scaleratio": 0.48261834319526625,
    "annots": [
        {
            "personID": 0,
            "bbox": [
                24.864367816091956,
                346.0291187739464,
                1388.2605363984676,
                888.9011494252874
            ],
            "keypoints": [
                [
                    1062.951724137931,
                    430.9823754789272,
                    1.0
                ],
                [
                    1031.8712643678161,
                    472.4229885057471,
                    1.0
                ],
                [
                    996.6467432950192,
                    426.8383141762452,
                    1.0
                ],
                [
                    1125.112643678161,
                    424.7662835249042,
                    1.0
                ],
                [
                    1230.7862068965517,
                    435.1264367816092,
                    1.0
                ],
                [
                    1040.15938697318,
                    505.5754789272031,
                    1.0
                ],
                [
                    1178.9854406130269,
                    495.2153256704981,
                    1.0
                ],
                [
                    1259.7946360153258,
                    493.1432950191571,
                    1.0
                ],
                [
                    766.6513409961686,
                    528.3678160919541,
                    1.0
                ],
                [
                    509.71954022988507,
                    638.1854406130268,
                    1.0
                ],
                [
                    383.3256704980843,
                    754.2191570881226,
                    1.0
                ],
                [
                    795.6597701149426,
                    611.2490421455939,
                    1.0
                ],
                [
                    526.295785440613,
                    576.0245210727969,
                    1.0
                ],
                [
                    219.6352490421456,
                    648.5455938697319,
                    1.0
                ],
                [
                    47.65670498084291,
                    617.4651340996169,
                    1.0
                ],
                [
                    271.4360153256705,
                    828.8122605363985,
                    1.0
                ],
                [
                    1305.3793103448277,
                    491.0712643678161,
                    1.0
                ],
                [
                    1305.3793103448277,
                    449.63065134099617,
                    1.0
                ]
            ]
        }
    ],
    "detect_feet": false,
    "isKeyframe": false
}