{
    "filename": "D:/DELL/Downloads/73\\GX0101111084.jpg",
    "height": 1520,
    "width": 2704,
    "scaleratio": 0.48261834319526625,
    "annots": [
        {
            "personID": 0,
            "bbox": [
                290.0842911877395,
                333.5969348659004,
                2101.03908045977,
                1009.0789272030652
            ],
            "keypoints": [
                [
                    1297.0911877394637,
                    565.664367816092,
                    1.0
                ],
                [
                    1272.2268199233717,
                    592.6007662835249,
                    1.0
                ],
                [
                    1282.5869731800767,
                    615.3931034482758,
                    1.0
                ],
                [
                    1373.7563218390806,
                    559.448275862069,
                    1.0
                ],
                [
                    0.0,
                    0.0,
                    0.0
                ],
                [
                    1210.0659003831418,
                    598.8168582375479,
                    1.0
                ],
                [
                    1359.2521072796935,
                    528.3678160919541,
                    1.0
                ],
                [
                    0.0,
                    0.0,
                    0.0
                ],
                [
                    1009.0789272030652,
                    706.5624521072797,
                    1.0
                ],
                [
                    803.9478927203065,
                    673.4099616858238,
                    1.0
                ],
                [
                    650.6176245210728,
                    729.3547892720306,
                    1.0
                ],
                [
                    977.9984674329502,
                    658.9057471264368,
                    1.0
                ],
                [
                    785.2996168582375,
                    623.6812260536399,
                    1.0
                ],
                [
                    613.3210727969349,
                    756.2911877394637,
                    1.0
                ],
                [
                    532.511877394636,
                    812.2360153256706,
                    1.0
                ],
                [
                    538.727969348659,
                    692.0582375478928,
                    1.0
                ],
                [
                    0.0,
                    0.0,
                    0.0
                ],
                [
                    0.0,
                    0.0,
                    0.0
                ]
            ]
        }
    ],
    "detect_feet": false,
    "isKeyframe": false
}