{
    "filename": "D:/DELL/Downloads/73\\GX0101111576.jpg",
    "height": 1520,
    "width": 2704,
    "scaleratio": 0.48261834319526625,
    "annots": [
        {
            "personID": 0,
            "bbox": [
                53.8727969348659,
                252.78773946360155,
                1506.3662835249042,
                797.7318007662835
            ],
            "keypoints": [
                [
                    886.8291187739464,
                    426.8383141762452,
                    1.0
                ],
                [
                    905.4773946360153,
                    476.56704980842915,
                    1.0
                ],
                [
                    915.8375478927203,
                    499.3593869731801,
                    1.0
                ],
                [
                    1017.3670498084292,
                    435.1264367816092,
                    1.0
                ],
                [
                    1116.8245210727969,
                    418.5501915708812,
                    1.0
                ],
                [
                    839.1724137931035,
                    453.7747126436782,
                    1.0
                ],
                [
                    677.5540229885057,
                    493.1432950191571,
                    1.0
                ],
                [
                    538.727969348659,
                    497.2873563218391,
                    1.0
                ],
                [
                    596.744827586207,
                    522.1517241379311,
                    1.0
                ],
                [
                    341.88505747126436,
                    526.295785440613,
                    1.0
                ],
                [
                    186.48275862068965,
                    673.4099616858238,
                    1.0
                ],
                [
                    580.168582375479,
                    542.872030651341,
                    1.0
                ],
                [
                    329.4528735632184,
                    501.4314176245211,
                    1.0
                ],
                [
                    211.34712643678162,
                    687.9141762452108,
                    1.0
                ],
                [
                    0.0,
                    0.0,
                    0.0
                ],
                [
                    0.0,
                    0.0,
                    0.0
                ],
                [
                    470.35095785440615,
                    538.727969348659,
                    1.0
                ],
                [
                    1154.1210727969349,
                    404.04597701149424,
                    1.0
                ]
            ]
        }
    ],
    "detect_feet": false,
    "isKeyframe": false
}